README.rst
setup.py
src/esc/__init__.py
src/esc.egg-info/PKG-INFO
src/esc.egg-info/SOURCES.txt
src/esc.egg-info/dependency_links.txt
src/esc.egg-info/requires.txt
src/esc.egg-info/top_level.txt